odoo/addons/stock_picking_partner_note/README.rst
odoo/addons/stock_picking_partner_note/__init__.py
odoo/addons/stock_picking_partner_note/__manifest__.py
odoo/addons/stock_picking_partner_note/i18n/fr.po
odoo/addons/stock_picking_partner_note/i18n/it.po
odoo/addons/stock_picking_partner_note/i18n/pt_BR.po
odoo/addons/stock_picking_partner_note/i18n/stock_picking_partner_note.pot
odoo/addons/stock_picking_partner_note/models/__init__.py
odoo/addons/stock_picking_partner_note/models/res_company.py
odoo/addons/stock_picking_partner_note/models/res_config_settings.py
odoo/addons/stock_picking_partner_note/models/res_partner.py
odoo/addons/stock_picking_partner_note/models/stock_picking.py
odoo/addons/stock_picking_partner_note/models/stock_picking_note.py
odoo/addons/stock_picking_partner_note/models/stock_picking_note_type.py
odoo/addons/stock_picking_partner_note/models/stock_picking_type.py
odoo/addons/stock_picking_partner_note/readme/CONFIGURE.md
odoo/addons/stock_picking_partner_note/readme/CONTRIBUTORS.md
odoo/addons/stock_picking_partner_note/readme/DESCRIPTION.md
odoo/addons/stock_picking_partner_note/security/ir.model.access.csv
odoo/addons/stock_picking_partner_note/static/description/icon.png
odoo/addons/stock_picking_partner_note/static/description/index.html
odoo/addons/stock_picking_partner_note/tests/__init__.py
odoo/addons/stock_picking_partner_note/tests/test_stock_picking_partner_note.py
odoo/addons/stock_picking_partner_note/views/res_config_settings.xml
odoo/addons/stock_picking_partner_note/views/res_partner.xml
odoo/addons/stock_picking_partner_note/views/stock_picking_note.xml
odoo/addons/stock_picking_partner_note/views/stock_picking_note_type.xml
odoo/addons/stock_picking_partner_note/views/stock_picking_partner_note_menus.xml
odoo/addons/stock_picking_partner_note/views/stock_picking_type.xml
odoo_addon_stock_picking_partner_note-18.0.1.0.0.4.dist-info/METADATA
odoo_addon_stock_picking_partner_note-18.0.1.0.0.4.dist-info/WHEEL
odoo_addon_stock_picking_partner_note-18.0.1.0.0.4.dist-info/top_level.txt
odoo_addon_stock_picking_partner_note-18.0.1.0.0.4.dist-info/RECORD
